sygra/__init__.py
sygra/config/configuration.yaml
sygra/config/models.yaml
sygra/config/payload_cfg.json
sygra/configuration/__init__.py
sygra/configuration/loader.py
sygra/core/__init__.py
sygra/core/base_task_executor.py
sygra/core/judge_task_executor.py
sygra/core/resumable_execution.py
sygra/core/dataset/data_handler_base.py
sygra/core/dataset/dataset_config.py
sygra/core/dataset/dataset_processor.py
sygra/core/dataset/file_handler.py
sygra/core/dataset/huggingface_handler.py
sygra/core/dataset/servicenow_handler.py
sygra/core/eval/metrics/base_metric_metadata.py
sygra/core/eval/metrics/aggregator_metrics/accuracy.py
sygra/core/eval/metrics/aggregator_metrics/aggregator_metric_registry.py
sygra/core/eval/metrics/aggregator_metrics/base_aggregator_metric.py
sygra/core/eval/metrics/aggregator_metrics/f1_score.py
sygra/core/eval/metrics/aggregator_metrics/precision.py
sygra/core/eval/metrics/aggregator_metrics/recall.py
sygra/core/eval/metrics/unit_metrics/base_unit_metric.py
sygra/core/eval/metrics/unit_metrics/exact_match.py
sygra/core/eval/metrics/unit_metrics/unit_metric_result.py
sygra/core/graph/__init__.py
sygra/core/graph/backend_factory.py
sygra/core/graph/graph_config.py
sygra/core/graph/graph_postprocessor.py
sygra/core/graph/sygra_message.py
sygra/core/graph/sygra_state.py
sygra/core/graph/edges/edge_factory.py
sygra/core/graph/functions/edge_condition.py
sygra/core/graph/functions/lambda_function.py
sygra/core/graph/functions/node_processor.py
sygra/core/graph/langgraph/__init__.py
sygra/core/graph/langgraph/graph_builder.py
sygra/core/graph/langgraph/langchain_callback.py
sygra/core/graph/langgraph/langgraph_factory.py
sygra/core/graph/langgraph/langgraph_state.py
sygra/core/graph/nodes/agent_node.py
sygra/core/graph/nodes/base_node.py
sygra/core/graph/nodes/connector_node.py
sygra/core/graph/nodes/lambda_node.py
sygra/core/graph/nodes/llm_node.py
sygra/core/graph/nodes/multi_llm_node.py
sygra/core/graph/nodes/node_utils.py
sygra-2.0.0.dist-info/METADATA
sygra-2.0.0.dist-info/WHEEL
sygra-2.0.0.dist-info/licenses/LICENSE
sygra-2.0.0.dist-info/RECORD
