Metadata-Version: 2.4
Name: sygra
Version: 2.0.0
Summary: Graph-oriented Synthetic data generation Pipeline library
Project-URL: Homepage, https://github.com/ServiceNow/SyGra
Project-URL: Documentation, https://servicenow.github.io/SyGra
Project-URL: Releases, https://github.com/ServiceNow/SyGra/releases
Project-URL: Issues, https://github.com/ServiceNow/SyGra/issues
Project-URL: Discussions, https://github.com/ServiceNow/SyGra/discussions
Author-email: "Bidyapati Pradhan, Surajit Dasgupta, Amit Kumar Saha, Sriram Puttagunta, Omkar Anustoop, Vipul Mittal, Gopal Sarda" <sygra_team@servicenow.com>
Maintainer-email: SyGra Team <sygra_team@servicenow.com>
License: Apache-2.0
License-File: LICENSE
Keywords: data generation,data quality,dpo,fine-tuning,graph,llm,metadata tagging,nlp,sft,synthetic data
Classifier: Intended Audience :: Developers
Classifier: Intended Audience :: Science/Research
Classifier: License :: OSI Approved :: Apache Software License
Classifier: Operating System :: OS Independent
Classifier: Programming Language :: Python :: 3
Classifier: Programming Language :: Python :: 3.9
Classifier: Programming Language :: Python :: 3.10
Classifier: Programming Language :: Python :: 3.11
Classifier: Topic :: Scientific/Engineering :: Artificial Intelligence
Classifier: Topic :: Software Development :: Libraries
Requires-Python: !=3.9.7,<3.12,>=3.9
Requires-Dist: aiohttp<4.0,>=3.12
Requires-Dist: boto3<2.0.0,>=1.40.71
Requires-Dist: datasets<=4.0.0
Requires-Dist: fasttext-wheel<0.10.0,>=0.9.2
Requires-Dist: fasttext<1.0,>=0.9
Requires-Dist: google-auth<3.0.0,>=2.43.0
Requires-Dist: google-cloud-aiplatform<2.0.0,>=1.128.0
Requires-Dist: grandalf<1.0,>=0.8
Requires-Dist: httpx-sse<0.5,>=0.4
Requires-Dist: httpx<0.29,>=0.28
Requires-Dist: huggingface-hub<1.0,>=0.34
Requires-Dist: jinja2<4.0,>=3.1
Requires-Dist: langchain-community<1.0,>=0.3
Requires-Dist: langchain-core<1.0,>=0.3
Requires-Dist: langchain-mistralai<1.0,>=0.2
Requires-Dist: langchain-openai<1.0,>=0.3
Requires-Dist: langgraph<1.0,>=0.6
Requires-Dist: lexicalrichness<1.0,>=0.5
Requires-Dist: litellm<2.0.0,>=1.79.3
Requires-Dist: mistralai<2.0,>=1.9
Requires-Dist: mlxtend<1.0,>=0.23
Requires-Dist: ollama<1.0,>=0.5
Requires-Dist: openai<2.0,>=1.107
Requires-Dist: pandarallel<2.0,>=1.6
Requires-Dist: pathvalidate<4.0,>=3.3
Requires-Dist: protobuf<7.0,>=6.32
Requires-Dist: pysnc<1.2.0,>=1.1.0
Requires-Dist: pyyaml<7.0,>=6.0
Requires-Dist: sentence-transformers<6.0,>=5.1
Requires-Dist: sentencepiece<1.0,>=0.2
Requires-Dist: soundfile<1.0,>=0.13
Requires-Dist: torch<3.0,>=2.8
Requires-Dist: transformers<4.57,>=4.56
Requires-Dist: types-pyyaml<7.0,>=6.0
Requires-Dist: ujson<6.0,>=5.11
Provides-Extra: dev
Requires-Dist: black<26.0,>=25.1; extra == 'dev'
Requires-Dist: build<2.0,>=1.3; extra == 'dev'
Requires-Dist: isort<7.0,>=6.0; extra == 'dev'
Requires-Dist: mkdocs-include-markdown-plugin<8.0,>=7.1; extra == 'dev'
Requires-Dist: mkdocs-material<10.0,>=9.6; extra == 'dev'
Requires-Dist: mkdocs<2.0,>=1.6; extra == 'dev'
Requires-Dist: mypy<2.0,>=1.17; extra == 'dev'
Requires-Dist: pytest-asyncio<2.0,>=1.1; extra == 'dev'
Requires-Dist: pytest<9.0,>=8.4; extra == 'dev'
Requires-Dist: ruff<1.0,>=0.13; extra == 'dev'
Requires-Dist: twine<7.0,>=6.2; extra == 'dev'
Requires-Dist: types-requests<3.0,>=2.31; extra == 'dev'
Provides-Extra: ui
Requires-Dist: plotly>=6.5.0; extra == 'ui'
Requires-Dist: streamlit-agraph<1.0,>=0.0; extra == 'ui'
Requires-Dist: streamlit-autorefresh<2.0,>=1.0; extra == 'ui'
Requires-Dist: streamlit-flow-component<2.0,>=1.6; extra == 'ui'
Requires-Dist: streamlit<2.0,>=1.49; (python_version != '3.9.7') and extra == 'ui'
Requires-Dist: watchdog<7.0,>=6.0; extra == 'ui'
